.DS_Store
blaze/__init__.py
blaze/blaze.py
blaze_forecaster-0.1.0.dist-info/METADATA
blaze_forecaster-0.1.0.dist-info/WHEEL
blaze_forecaster-0.1.0.dist-info/top_level.txt
blaze_forecaster-0.1.0.dist-info/RECORD
