Metadata-Version: 2.1
Name: blaze-forecaster
Version: 0.1.0
Summary: Forecaster that combines the strengths of SARIMA and Prophet.
Author: Ysabel Chen
Keywords: python,forecaster
Classifier: Programming Language :: Python :: 3
Classifier: Operating System :: MacOS :: MacOS X
Classifier: Operating System :: Microsoft :: Windows
